[
  {
    "op": "core/text-transform",
    "engineConfig": {
      "facets": [],
      "mode": "row-based"
    },
    "columnName": "Número de archivo",
    "expression": "value.toNumber()",
    "onError": "keep-original",
    "repeat": false,
    "repeatCount": 10,
    "description": "Text transform on cells in column Número de archivo using expression value.toNumber()"
  },
  {
    "op": "core/column-rename",
    "oldColumnName": "Solar",
    "newColumnName": "Solar (m2)",
    "description": "Rename column Solar to Solar (m2)"
  },
  {
    "op": "core/text-transform",
    "engineConfig": {
      "facets": [],
      "mode": "row-based"
    },
    "columnName": "Solar (m2)",
    "expression": "grel:value.replace(\" m2\", \"\")",
    "onError": "keep-original",
    "repeat": false,
    "repeatCount": 10,
    "description": "Text transform on cells in column Solar (m2) using expression grel:value.replace(\" m2\", \"\")"
  },
  {
    "op": "core/text-transform",
    "engineConfig": {
      "facets": [],
      "mode": "row-based"
    },
    "columnName": "Solar (m2)",
    "expression": "value.toNumber()",
    "onError": "keep-original",
    "repeat": false,
    "repeatCount": 10,
    "description": "Text transform on cells in column Solar (m2) using expression value.toNumber()"
  },
  {
    "op": "core/text-transform",
    "engineConfig": {
      "facets": [],
      "mode": "row-based"
    },
    "columnName": "Situación Destino",
    "expression": "grel:value.replace(\"NUM\", \"Nº\")",
    "onError": "keep-original",
    "repeat": false,
    "repeatCount": 10,
    "description": "Text transform on cells in column Situación Destino using expression grel:value.replace(\"NUM\", \"Nº\")"
  },
  {
    "op": "core/text-transform",
    "engineConfig": {
      "facets": [],
      "mode": "row-based"
    },
    "columnName": "Situación Destino",
    "expression": "grel:value.replace(\" C/ \", \" CALLE \")",
    "onError": "keep-original",
    "repeat": false,
    "repeatCount": 10,
    "description": "Text transform on cells in column Situación Destino using expression grel:value.replace(\" C/ \", \" CALLE \")"
  }
]